README.md
setup.py
RespawnSimulator/__init__.py
RespawnSimulator/character.py
RespawnSimulator/event.py
RespawnSimulator/property.py
RespawnSimulator/utils.py
RespawnSimulator.egg-info/PKG-INFO
RespawnSimulator.egg-info/SOURCES.txt
RespawnSimulator.egg-info/dependency_links.txt
RespawnSimulator.egg-info/top_level.txt