Metadata-Version: 2.1
Name: RespawnSimulator
Version: 1.0.4
Summary: A respawn simulator framework
Home-page: UNKNOWN
Author: N0P3
Author-email: n0p3@qq.com
License: UNKNOWN
Platform: UNKNOWN
